easyserial/__init__.py
easyserial/easyserial.py
easyserial/errors.py
easyserial/scripts/__init__.py
easyserial/scripts/logger.py
easyserial-0.2.0.dist-info/LICENSE
easyserial-0.2.0.dist-info/METADATA
easyserial-0.2.0.dist-info/WHEEL
easyserial-0.2.0.dist-info/entry_points.txt
easyserial-0.2.0.dist-info/top_level.txt
easyserial-0.2.0.dist-info/RECORD
