Metadata-Version: 2.1
Name: easyserial
Version: 0.2.0
Summary: Serial protocol to send and receive data effortlessly
Home-page: https://gitlab.com/altairLab/elasticteam/forecast/easy-serial
Author: Matteo Meneghetti
Author-email: matteo@meneghetti.dev
License: MIT
Platform: UNKNOWN
Classifier: Programming Language :: Python :: 3
Classifier: License :: OSI Approved :: MIT License
Classifier: Operating System :: OS Independent
Requires-Dist: pyserial
